ustvgo_iptv/__init__.py
ustvgo_iptv/channels.json
ustvgo_iptv/ustvgo_iptv.py
ustvgo_iptv-0.1.12.dist-info/METADATA
ustvgo_iptv-0.1.12.dist-info/WHEEL
ustvgo_iptv-0.1.12.dist-info/entry_points.txt
ustvgo_iptv-0.1.12.dist-info/top_level.txt
ustvgo_iptv-0.1.12.dist-info/RECORD
