Metadata-Version: 2.1
Name: ustvgo-iptv
Version: 0.1.12
Summary: USTVGO Free IPTV
Home-page: https://github.com/interlark/ustvgo-iptv
Author: Andy Trofimov
Author-email: interlark@gmail.com
License: MIT
Keywords: ustvgo,iptv,m3u8,playlist,tvguide,english
Classifier: Topic :: Internet
Classifier: Topic :: Utilities
Classifier: Operating System :: OS Independent
Classifier: Programming Language :: Python :: 3 :: Only
Classifier: Programming Language :: Python :: 3.7
Classifier: Programming Language :: Python :: 3.8
Classifier: Programming Language :: Python :: 3.9
Classifier: Programming Language :: Python :: 3.10
Classifier: License :: OSI Approved :: MIT License
Requires-Python: >=3.7.4
Requires-Dist: aiohttp (>=3.8.1)
Requires-Dist: tqdm (>=4.64.0)
Requires-Dist: netifaces (>=0.11.0)
Requires-Dist: furl (>=2.1.3)
Requires-Dist: typing-extensions (>=3.7.4) ; python_version < "3.8"
Provides-Extra: dev
Requires-Dist: wheel (<0.38,>=0.36.2) ; extra == 'dev'
Requires-Dist: flake8 (>=4.0.1) ; extra == 'dev'
Requires-Dist: mypy (>=0.961) ; extra == 'dev'
